{
	"buffer": true,
	"telegram": true,
	"hackernews": true,
	"odnoklassniki": true,
	"facebook": true,
	"weibo": true,
	"xing": true,
	"evernote": true,
	"instapaper": true,
	"whatsapp": true,
	"twitter": true,
	"twitter_username": "4NPowerfulBlog",
	"line": true,
	"yammer": true,
	"vk": true,
	"pocket": true,
	"skype": true,
	"sms": true,
	"flipboard": true,
	"wordpress": true,
	"quora": true,
	"pinterest": true,
	"baidu": true,
	"viber": true,
	"stumbleupon": true,
	"email": true,
	"tumblr": true,
	"linkedin": true,
	"reddit": true
}